{
 "actions": [],
 "allow_import": 1,
 "autoname": "naming_series:",
 "creation": "2023-07-30 23:18:49.678496",
 "default_view": "List",
 "doctype": "DocType",
 "engine": "InnoDB",
 "field_order": [
  "customer_section",
  "title",
  "naming_series",
  "member",
  "member_name",
  "tax_id",
  "is_return",
  "column_break1",
  "company",
  "company_tax_id",
  "posting_date",
  "posting_time",
  "due_date",
  "return_against",
  "address_and_contact",
  "customer_address",
  "address_display",
  "contact_person",
  "contact_display",
  "contact_mobile",
  "contact_email",
  "territory",
  "col_break4",
  "shipping_address",
  "company_address_display",
  "sec_warehouse",
  "set_warehouse",
  "items_section",
  "items",
  "section_break_30",
  "total_qty",
  "column_break_32",
  "net_total",
  "amended_from"
 ],
 "fields": [
  {
   "fieldname": "customer_section",
   "fieldtype": "Section Break",
   "hide_days": 1,
   "hide_seconds": 1,
   "options": "fa fa-user"
  },
  {
   "allow_on_submit": 1,
   "default": "{member_name}",
   "fieldname": "title",
   "fieldtype": "Data",
   "hidden": 1,
   "hide_days": 1,
   "hide_seconds": 1,
   "label": "Title",
   "no_copy": 1,
   "print_hide": 1
  },
  {
   "bold": 1,
   "fieldname": "naming_series",
   "fieldtype": "Select",
   "hide_days": 1,
   "hide_seconds": 1,
   "in_list_view": 1,
   "label": "Series",
   "no_copy": 1,
   "oldfieldname": "naming_series",
   "oldfieldtype": "Select",
   "options": "ACC-SINV-.YYYY.-",
   "print_hide": 1,
   "reqd": 1,
   "set_only_once": 1
  },
  {
   "bold": 1,
   "fieldname": "member",
   "fieldtype": "Link",
   "hide_days": 1,
   "hide_seconds": 1,
   "in_standard_filter": 1,
   "label": "Member",
   "oldfieldname": "customer",
   "oldfieldtype": "Link",
   "options": "Member",
   "print_hide": 1,
   "search_index": 1
  },
  {
   "bold": 1,
   "fetch_from": "Member.member_name",
   "fieldname": "member_name",
   "fieldtype": "Small Text",
   "hide_days": 1,
   "hide_seconds": 1,
   "in_global_search": 1,
   "label": "Member Name",
   "oldfieldname": "customer_name",
   "oldfieldtype": "Data",
   "read_only": 1
  },
  {
   "fieldname": "tax_id",
   "fieldtype": "Data",
   "hide_days": 1,
   "hide_seconds": 1,
   "label": "Tax Id",
   "print_hide": 1,
   "read_only": 1
  },
  {
   "default": "0",
   "fieldname": "is_return",
   "fieldtype": "Check",
   "hide_days": 1,
   "hide_seconds": 1,
   "label": "Is Return (Credit Note)",
   "no_copy": 1,
   "print_hide": 1
  },
  {
   "fieldname": "column_break1",
   "fieldtype": "Column Break",
   "hide_days": 1,
   "hide_seconds": 1,
   "oldfieldtype": "Column Break"
  },
  {
   "fieldname": "company",
   "fieldtype": "Link",
   "hide_days": 1,
   "hide_seconds": 1,
   "in_list_view": 1,
   "in_standard_filter": 1,
   "label": "Company",
   "oldfieldname": "company",
   "oldfieldtype": "Link",
   "options": "Company",
   "print_hide": 1,
   "remember_last_selected_value": 1,
   "reqd": 1
  },
  {
   "fetch_from": "company.tax_id",
   "fieldname": "company_tax_id",
   "fieldtype": "Data",
   "label": "Company Tax ID",
   "read_only": 1
  },
  {
   "bold": 1,
   "default": "Today",
   "fieldname": "posting_date",
   "fieldtype": "Date",
   "hide_days": 1,
   "hide_seconds": 1,
   "in_list_view": 1,
   "label": "Date",
   "no_copy": 1,
   "oldfieldname": "posting_date",
   "oldfieldtype": "Date",
   "reqd": 1,
   "search_index": 1
  },
  {
   "fieldname": "posting_time",
   "fieldtype": "Time",
   "hide_days": 1,
   "hide_seconds": 1,
   "label": "Posting Time",
   "no_copy": 1,
   "oldfieldname": "posting_time",
   "oldfieldtype": "Time",
   "print_hide": 1
  },
  {
   "fieldname": "due_date",
   "fieldtype": "Date",
   "hide_days": 1,
   "hide_seconds": 1,
   "label": "Payment Due Date",
   "no_copy": 1,
   "oldfieldname": "due_date",
   "oldfieldtype": "Date"
  },
  {
   "depends_on": "eval:doc.return_against || doc.is_debit_note",
   "fieldname": "return_against",
   "fieldtype": "Link",
   "hide_days": 1,
   "hide_seconds": 1,
   "label": "Return Against",
   "no_copy": 1,
   "options": "Sales Invoice",
   "print_hide": 1,
   "read_only_depends_on": "eval:doc.is_return",
   "search_index": 1
  },
  {
   "collapsible": 1,
   "fieldname": "address_and_contact",
   "fieldtype": "Section Break",
   "hide_days": 1,
   "hide_seconds": 1,
   "label": "Address and Contact"
  },
  {
   "fieldname": "customer_address",
   "fieldtype": "Link",
   "hide_days": 1,
   "hide_seconds": 1,
   "label": "Member Address",
   "options": "Address",
   "print_hide": 1
  },
  {
   "fieldname": "address_display",
   "fieldtype": "Small Text",
   "hide_days": 1,
   "hide_seconds": 1,
   "label": "Member Address",
   "read_only": 1
  },
  {
   "fieldname": "contact_person",
   "fieldtype": "Link",
   "hide_days": 1,
   "hide_seconds": 1,
   "in_global_search": 1,
   "label": "Contact Person",
   "options": "Contact",
   "print_hide": 1
  },
  {
   "fieldname": "contact_display",
   "fieldtype": "Small Text",
   "hide_days": 1,
   "hide_seconds": 1,
   "label": "Contact",
   "read_only": 1
  },
  {
   "fieldname": "contact_mobile",
   "fieldtype": "Small Text",
   "hidden": 1,
   "hide_days": 1,
   "hide_seconds": 1,
   "label": "Mobile No",
   "read_only": 1
  },
  {
   "fieldname": "contact_email",
   "fieldtype": "Data",
   "hidden": 1,
   "hide_days": 1,
   "hide_seconds": 1,
   "label": "Contact Email",
   "options": "Email",
   "print_hide": 1,
   "read_only": 1
  },
  {
   "fieldname": "territory",
   "fieldtype": "Link",
   "hide_days": 1,
   "hide_seconds": 1,
   "label": "Territory",
   "options": "Territory",
   "print_hide": 1
  },
  {
   "fieldname": "col_break4",
   "fieldtype": "Column Break",
   "hide_days": 1,
   "hide_seconds": 1
  },
  {
   "fieldname": "shipping_address",
   "fieldtype": "Small Text",
   "hide_days": 1,
   "hide_seconds": 1,
   "label": "Shipping Address",
   "print_hide": 1,
   "read_only": 1
  },
  {
   "fieldname": "company_address_display",
   "fieldtype": "Small Text",
   "hidden": 1,
   "hide_days": 1,
   "hide_seconds": 1,
   "label": "Company Address",
   "print_hide": 1,
   "read_only": 1
  },
  {
   "fieldname": "sec_warehouse",
   "fieldtype": "Section Break",
   "hide_days": 1,
   "hide_seconds": 1,
   "label": "Warehouse"
  },
  {
   "depends_on": "update_stock",
   "fieldname": "set_warehouse",
   "fieldtype": "Link",
   "hide_days": 1,
   "hide_seconds": 1,
   "label": "Source Warehouse",
   "options": "Warehouse",
   "print_hide": 1
  },
  {
   "fieldname": "items_section",
   "fieldtype": "Section Break",
   "hide_days": 1,
   "hide_seconds": 1,
   "label": "Items",
   "oldfieldtype": "Section Break",
   "options": "fa fa-shopping-cart"
  },
  {
   "allow_bulk_edit": 1,
   "fieldname": "items",
   "fieldtype": "Table",
   "hide_days": 1,
   "hide_seconds": 1,
   "label": "Items",
   "oldfieldname": "entries",
   "oldfieldtype": "Table",
   "options": "Sales Invoice Item",
   "reqd": 1
  },
  {
   "fieldname": "section_break_30",
   "fieldtype": "Section Break",
   "hide_days": 1,
   "hide_seconds": 1
  },
  {
   "fieldname": "total_qty",
   "fieldtype": "Float",
   "hide_days": 1,
   "hide_seconds": 1,
   "label": "Total Quantity",
   "read_only": 1
  },
  {
   "fieldname": "column_break_32",
   "fieldtype": "Column Break",
   "hide_days": 1,
   "hide_seconds": 1
  },
  {
   "fieldname": "net_total",
   "fieldtype": "Currency",
   "hide_days": 1,
   "hide_seconds": 1,
   "label": "Net Total",
   "options": "currency",
   "print_hide": 1,
   "read_only": 1
  },
  {
   "fieldname": "amended_from",
   "fieldtype": "Link",
   "label": "Amended From",
   "no_copy": 1,
   "options": "Sales Invoice",
   "print_hide": 1,
   "read_only": 1
  }
 ],
 "icon": "fa fa-file-text",
 "is_submittable": 1,
 "links": [],
 "modified": "2023-07-30 23:30:46.535106",
 "modified_by": "Administrator",
 "module": "Gymkhana",
 "name": "Sales Invoice",
 "name_case": "Title Case",
 "naming_rule": "By \"Naming Series\" field",
 "owner": "Administrator",
 "permissions": [
  {
   "amend": 1,
   "cancel": 1,
   "create": 1,
   "delete": 1,
   "email": 1,
   "print": 1,
   "read": 1,
   "report": 1,
   "role": "Accounts Manager",
   "share": 1,
   "submit": 1,
   "write": 1
  },
  {
   "amend": 1,
   "create": 1,
   "email": 1,
   "print": 1,
   "read": 1,
   "report": 1,
   "role": "Accounts User",
   "share": 1,
   "submit": 1,
   "write": 1
  },
  {
   "permlevel": 1,
   "read": 1,
   "role": "Accounts Manager",
   "write": 1
  },
  {
   "permlevel": 1,
   "read": 1,
   "role": "All"
  }
 ],
 "quick_entry": 1,
 "search_fields": "posting_date, due_date, member_name",
 "show_name_in_global_search": 1,
 "sort_field": "modified",
 "sort_order": "DESC",
 "states": [],
 "timeline_field": "member",
 "title_field": "title",
 "track_changes": 1,
 "track_seen": 1
}